at_cascade/__init__.py
at_cascade/add_log_entry.py
at_cascade/avgint_parent_grid.py
at_cascade/bilinear.py
at_cascade/cascade_root_node.py
at_cascade/check_cascade_node.py
at_cascade/check_log.py
at_cascade/clear_shared.py
at_cascade/com_cov_reference.py
at_cascade/continue_cascade.py
at_cascade/copy_other_tbl.py
at_cascade/copy_root_db.py
at_cascade/create_all_node_db.py
at_cascade/create_job_table.py
at_cascade/create_shift_db.py
at_cascade/data_include.py
at_cascade/empty_avgint_table.py
at_cascade/empty_directory.py
at_cascade/extract_avgint.py
at_cascade/fit_one_job.py
at_cascade/fit_one_process.py
at_cascade/fit_or_root_class.py
at_cascade/fit_parallel.py
at_cascade/get_cov_info.py
at_cascade/get_database_dir.py
at_cascade/get_fit_children.py
at_cascade/get_fit_integrand.py
at_cascade/get_freeze_dict.py
at_cascade/get_parent_node.py
at_cascade/get_var_id.py
at_cascade/job_descendant.py
at_cascade/map_shared.py
at_cascade/move_table.py
at_cascade/no_ode_fit.py
at_cascade/omega_constraint.py
at_cascade/table_exists.py
at_cascade/table_name2id.py
at_cascade/csv/__init__.py
at_cascade/csv/ancestor_fit.py
at_cascade/csv/check_table.py
at_cascade/csv/covariate_avg.py
at_cascade/csv/covariate_both.py
at_cascade/csv/covariate_same.py
at_cascade/csv/covariate_spline.py
at_cascade/csv/empty_str.py
at_cascade/csv/fit.py
at_cascade/csv/get_header.py
at_cascade/csv/join_file.py
at_cascade/csv/pre_one_job.py
at_cascade/csv/pre_one_process.py
at_cascade/csv/pre_parallel.py
at_cascade/csv/pre_user.py
at_cascade/csv/predict.py
at_cascade/csv/read_table.py
at_cascade/csv/set_truth.py
at_cascade/csv/simulate.py
at_cascade/csv/write_table.py
at_cascade-2026.0.0.dist-info/METADATA
at_cascade-2026.0.0.dist-info/WHEEL
at_cascade-2026.0.0.dist-info/licenses/agpl-3.0.txt
at_cascade-2026.0.0.dist-info/RECORD
