Metadata-Version: 2.4
Name: at_cascade
Version: 2026.0.0
Summary: Cascading dismod_at from parent to child regions
Project-URL: Documentation, https://at-cascade.readthedocs.io
Project-URL: Homepage, https://at-cascade.readthedocs.io
Project-URL: Changelog, https://at-cascade.readthedocs.io/latest/release_notes.html
Project-URL: Repository, https://github.com/bradbell/at_cascade
Project-URL: Issues, https://github.com/bradbell/at_cascade/issues
Author-email: "Bradley M. Bell" <bradbell@seanet.com>
Maintainer-email: "Bradley M. Bell" <bradbell@seanet.com>
License-Expression: AGPL-3.0-or-later
License-File: agpl-3.0.txt
Keywords: disease modeling,dismod_at,public health
Classifier: Operating System :: OS Independent
Classifier: Programming Language :: Python :: 3
Requires-Python: >=3.8
Requires-Dist: dismod-at
Requires-Dist: numpy
Requires-Dist: scipy
